Metadata-Version: 2.1
Name: patternal
Version: 0.0.1
Summary: Creates patterns
Author: Arihant Pal
Author-email: arihantpal2001@gmail.com
Keywords: python,pattern,star_pattern,star
Classifier: Development Status :: 1 - Planning
Classifier: Intended Audience :: Developers
Classifier: Programming Language :: Python :: 3
Classifier: Operating System :: Unix
Classifier: Operating System :: MacOS :: MacOS X
Classifier: Operating System :: Microsoft :: Windows
